dja_sepp/__init__.py
dja_sepp/psfex.py
dja_sepp/s3.py
dja_sepp/sepp.py
dja_sepp/sextractor.py
dja_sepp/tiles.py
dja_sepp/utils.py
dja_sepp/data/NIRCam_Filters-Throughput/F070W_mean_system_throughput.txt
dja_sepp/data/NIRCam_Filters-Throughput/F090W_mean_system_throughput.txt
dja_sepp/data/NIRCam_Filters-Throughput/F115W_mean_system_throughput.txt
dja_sepp/data/NIRCam_Filters-Throughput/F140M_mean_system_throughput.txt
dja_sepp/data/NIRCam_Filters-Throughput/F150W2_mean_system_throughput.txt
dja_sepp/data/NIRCam_Filters-Throughput/F150W_mean_system_throughput.txt
dja_sepp/data/NIRCam_Filters-Throughput/F162M_mean_system_throughput.txt
dja_sepp/data/NIRCam_Filters-Throughput/F164N_mean_system_throughput.txt
dja_sepp/data/NIRCam_Filters-Throughput/F182M_mean_system_throughput.txt
dja_sepp/data/NIRCam_Filters-Throughput/F187N_mean_system_throughput.txt
dja_sepp/data/NIRCam_Filters-Throughput/F200W_mean_system_throughput.txt
dja_sepp/data/NIRCam_Filters-Throughput/F210M_mean_system_throughput.txt
dja_sepp/data/NIRCam_Filters-Throughput/F212N_mean_system_throughput.txt
dja_sepp/data/NIRCam_Filters-Throughput/F250M_mean_system_throughput.txt
dja_sepp/data/NIRCam_Filters-Throughput/F277W_mean_system_throughput.txt
dja_sepp/data/NIRCam_Filters-Throughput/F300M_mean_system_throughput.txt
dja_sepp/data/NIRCam_Filters-Throughput/F322W2_mean_system_throughput.txt
dja_sepp/data/NIRCam_Filters-Throughput/F323N_mean_system_throughput.txt
dja_sepp/data/NIRCam_Filters-Throughput/F335M_mean_system_throughput.txt
dja_sepp/data/NIRCam_Filters-Throughput/F356W_mean_system_throughput.txt
dja_sepp/data/NIRCam_Filters-Throughput/F360M_mean_system_throughput.txt
dja_sepp/data/NIRCam_Filters-Throughput/F405N_mean_system_throughput.txt
dja_sepp/data/NIRCam_Filters-Throughput/F410M_mean_system_throughput.txt
dja_sepp/data/NIRCam_Filters-Throughput/F430M_mean_system_throughput.txt
dja_sepp/data/NIRCam_Filters-Throughput/F444W_mean_system_throughput.txt
dja_sepp-0.1.24.dist-info/LICENSE
dja_sepp-0.1.24.dist-info/METADATA
dja_sepp-0.1.24.dist-info/WHEEL
dja_sepp-0.1.24.dist-info/top_level.txt
dja_sepp-0.1.24.dist-info/RECORD
