Metadata-Version: 2.1
Name: dja_sepp
Version: 0.1.24
Summary: Package to run SourceXtractor++ on the DAWN JWST Archive
Author-email: Aurélien Genin <aurelien.genin@polytechnique.org>
Project-URL: Source, https://github.com/AstroAure/DJA-SEpp
Project-URL: DJA, https://dawn-cph.github.io/dja/
Classifier: Programming Language :: Python :: 3
Classifier: License :: OSI Approved :: MIT License
Classifier: Operating System :: OS Independent
Requires-Python: >=3.9
License-File: LICENSE
Requires-Dist: awscli
Requires-Dist: boto3
Requires-Dist: numpy
Requires-Dist: matplotlib
Requires-Dist: astropy
Requires-Dist: shapely
Requires-Dist: reproject
Requires-Dist: scikit-learn
